terra_billing_alert/__init__.py
terra_billing_alert/__main__.py
terra_billing_alert/alert_item.py
terra_billing_alert/alert_sender.py
terra_billing_alert/bucket.py
terra_billing_alert/cli.py
terra_billing_alert/datetime_util.py
terra_billing_alert/gcp_machine_type.py
terra_billing_alert/instance.py
terra_billing_alert/terra_util.py
terra_billing_alert/workflow.py
terra_billing_alert-0.1.7.data/scripts/terra_billing_alert
terra_billing_alert-0.1.7.dist-info/LICENSE
terra_billing_alert-0.1.7.dist-info/METADATA
terra_billing_alert-0.1.7.dist-info/WHEEL
terra_billing_alert-0.1.7.dist-info/top_level.txt
terra_billing_alert-0.1.7.dist-info/RECORD
