Metadata-Version: 2.1
Name: terra-billing-alert
Version: 0.1.7
Summary: Terra Billing Alert script for Google Cloud Function
Home-page: https://github.com/IGVF-DACC/terra-billing-alert
Author: Jin wook Lee
Author-email: leepc12@gmail.com
Classifier: Programming Language :: Python :: 3
Classifier: License :: OSI Approved :: MIT License
Classifier: Operating System :: POSIX :: Linux
Requires-Python: >=3.6
License-File: LICENSE
Requires-Dist: firecloud (==0.16.32)
Requires-Dist: pandas (==1.3.5)
Requires-Dist: pandas-gbq (==0.17.5)
Requires-Dist: common (==0.1.2)
Requires-Dist: slackclient (==2.9.4)
Requires-Dist: google-cloud-bigquery
Requires-Dist: ndg-httpsclient
